snkmt/__init__.py
snkmt/cli.py
snkmt/py.typed
snkmt/version.py
snkmt/console/__init__.py
snkmt/console/app.py
snkmt/console/command.py
snkmt/console/snkmt.tcss
snkmt/console/widgets.py
snkmt/console/views/__init__.py
snkmt/console/views/overview.py
snkmt/core/__init__.py
snkmt/core/config.py
snkmt/core/db/__init__.py
snkmt/core/db/alembic.ini
snkmt/core/db/session.py
snkmt/core/db/version.py
snkmt/core/db/alembic/README
snkmt/core/db/alembic/env.py
snkmt/core/db/alembic/script.py.mako
snkmt/core/db/alembic/versions/a088a7b93fe5_initial_schema.py
snkmt/core/db/alembic/versions/addc0edea736_remove_snkmt_db_version.py
snkmt/core/models/__init__.py
snkmt/core/models/base.py
snkmt/core/models/error.py
snkmt/core/models/file.py
snkmt/core/models/job.py
snkmt/core/models/rule.py
snkmt/core/models/workflow.py
snkmt/core/repository/__init__.py
snkmt/core/repository/sql.py
snkmt/types/__init__.py
snkmt/types/dto.py
snkmt/types/enums.py
snkmt-0.2.4.dist-info/METADATA
snkmt-0.2.4.dist-info/WHEEL
snkmt-0.2.4.dist-info/entry_points.txt
snkmt-0.2.4.dist-info/licenses/LICENSE
snkmt-0.2.4.dist-info/RECORD
