Metadata-Version: 2.4
Name: snkmt
Version: 0.2.4
Summary: Realtime monitoring of Snakemake workflows
Author-email: Cade Mirchandani <cmirchan@ucsc.edu>
License-File: LICENSE
Requires-Python: >=3.11
Requires-Dist: aiosqlite<0.22,>=0.21.0
Requires-Dist: alembic<2,>=1.16.1
Requires-Dist: beaupy<4,>=3.0.0
Requires-Dist: loguru<0.8,>=0.7.3
Requires-Dist: platformdirs<5,>=4.3.8
Requires-Dist: sqlalchemy>=2.0.38
Requires-Dist: textual>=3.1.1
Requires-Dist: typer>=0.15.3
